[
  {
    "id": "file-2025-08-30-le-vin-dans-les-voiles-0.html-la-mariole-2022",
    "blockId": "file-2025-08-30-le-vin-dans-les-voiles-0.html",
    "createdAt": "2025-08-30T00:00:00.000Z",
    "name": "La Mariole 2022",
    "description": "La Mariole 2022 est un rouge du sud qui n’a rien de sage. Derrière son allure ensoleillée, on retrouve des arômes de fruits noirs, une petite touche de cuir et une finale poivrée qui met l’eau à la bouche. Servi bien frais, il se glisse parfaitement dans l’ambiance d’un BBQ, avec des côtes levées caramélisées ou un hamburger bien gourmand.",
    "price": "24.70$",
    "image_url": "https://d3k81ch9hvuctc.cloudfront.net/company/VbA62P/images/42704e18-1dba-490d-97bd-1753d86f1fb5.png",
    "link": null,
    "agence": "Le vin dans les voiles",
    "disponibilite": "SAQ",
    "raw_data": {
      "name": "La Mariole 2022",
      "description": "La Mariole 2022 est un rouge du sud qui n’a rien de sage. Derrière son allure ensoleillée, on retrouve des arômes de fruits noirs, une petite touche de cuir et une finale poivrée qui met l’eau à la bouche. Servi bien frais, il se glisse parfaitement dans l’ambiance d’un BBQ, avec des côtes levées caramélisées ou un hamburger bien gourmand.",
      "price": "24.70$",
      "image_url": "https://d3k81ch9hvuctc.cloudfront.net/company/VbA62P/images/42704e18-1dba-490d-97bd-1753d86f1fb5.png",
      "link": null,
      "producer": "Domaine Ledogar",
      "region": null,
      "vintage": "2022",
      "grape_varieties": null,
      "alcohol_content": null,
      "volume": null,
      "disponibilite": "SAQ",
      "all_occurrences_raw_data": [
        {
          "name": "La Mariole 2022",
          "description": "La Mariole 2022 est un rouge du sud qui n’a rien de sage. Derrière son allure ensoleillée, on retrouve des arômes de fruits noirs, une petite touche de cuir et une finale poivrée qui met l’eau à la bouche. Servi bien frais, il se glisse parfaitement dans l’ambiance d’un BBQ, avec des côtes levées caramélisées ou un hamburger bien gourmand.",
          "price": "24.70$",
          "image_url": "https://d3k81ch9hvuctc.cloudfront.net/company/VbA62P/images/42704e18-1dba-490d-97bd-1753d86f1fb5.png",
          "link": null,
          "producer": "Domaine Ledogar",
          "region": null,
          "vintage": "2022",
          "grape_varieties": null,
          "alcohol_content": null,
          "volume": null,
          "disponibilite": "SAQ"
        }
      ],
      "agence_was_defaulted": false
    },
    "summary": "La Mariole 2022, un rouge ensoleillé du sud, séduit par ses arômes de fruits noirs, une touche de cuir et une finale poivrée, parfait pour animer vos barbecues estivaux."
  },
  {
    "id": "file-2025-08-30-le-vin-dans-les-voiles-0.html-excomungado-2021",
    "blockId": "file-2025-08-30-le-vin-dans-les-voiles-0.html",
    "createdAt": "2025-08-30T00:00:00.000Z",
    "name": "Excomungado 2021",
    "description": "Avec Excomungado 2021, cap sur le Douro, mais oubliez l’image des rouges portugais costauds et boisés. Ici, aucun passage en fût : l’élevage se fait en cuve d’acier inoxydable, ce qui préserve une fraîcheur et un croquant irrésistibles. Le vin reste concentré, mais gagne en légèreté et en fluidité — parfait pour un repas festif où l’on multiplie les assiettes à partager.",
    "price": "18.35$",
    "image_url": null,
    "link": null,
    "agence": "Le vin dans les voiles",
    "disponibilite": "SAQ",
    "raw_data": {
      "name": "Excomungado 2021",
      "description": "Avec Excomungado 2021, cap sur le Douro, mais oubliez l’image des rouges portugais costauds et boisés. Ici, aucun passage en fût : l’élevage se fait en cuve d’acier inoxydable, ce qui préserve une fraîcheur et un croquant irrésistibles. Le vin reste concentré, mais gagne en légèreté et en fluidité — parfait pour un repas festif où l’on multiplie les assiettes à partager.",
      "price": "18.35$",
      "image_url": null,
      "link": null,
      "producer": "Quinta Vale de Pios",
      "region": null,
      "vintage": "2021",
      "grape_varieties": null,
      "alcohol_content": null,
      "volume": null,
      "disponibilite": "SAQ",
      "all_occurrences_raw_data": [
        {
          "name": "Excomungado 2021",
          "description": "Avec Excomungado 2021, cap sur le Douro, mais oubliez l’image des rouges portugais costauds et boisés. Ici, aucun passage en fût : l’élevage se fait en cuve d’acier inoxydable, ce qui préserve une fraîcheur et un croquant irrésistibles. Le vin reste concentré, mais gagne en légèreté et en fluidité — parfait pour un repas festif où l’on multiplie les assiettes à partager.",
          "price": "18.35$",
          "image_url": null,
          "link": null,
          "producer": "Quinta Vale de Pios",
          "region": null,
          "vintage": "2021",
          "grape_varieties": null,
          "alcohol_content": null,
          "volume": null,
          "disponibilite": "SAQ"
        }
      ],
      "agence_was_defaulted": false
    },
    "summary": "Excomungado 2021 du Douro, sans fût, révèle une fraîcheur et un croquant irrésistibles, offrant une légèreté et une fluidité idéales pour des repas festifs à partager."
  },
  {
    "id": "file-2025-08-30-le-vin-dans-les-voiles-0.html-livia-2022",
    "blockId": "file-2025-08-30-le-vin-dans-les-voiles-0.html",
    "createdAt": "2025-08-30T00:00:00.000Z",
    "name": "Livia 2022",
    "description": "Pour un blanc vibrant d’émotion, Livia 2022, du projet Sous le Végétal, nous emmène sur l’île de Samos. Muscat salin et minéral, il conjugue profondeur, ampleur et élégance. Long en bouche, avec une finale gourmande, il gagne à être carafé pour révéler toute sa complexité. C’est le compagnon idéal des repas qui prennent leur temps, où la conversation coule aussi librement que le vin.",
    "price": "37.25$",
    "image_url": null,
    "link": null,
    "agence": "Le vin dans les voiles",
    "disponibilite": "SAQ",
    "raw_data": {
      "name": "Livia 2022",
      "description": "Pour un blanc vibrant d’émotion, Livia 2022, du projet Sous le Végétal, nous emmène sur l’île de Samos. Muscat salin et minéral, il conjugue profondeur, ampleur et élégance. Long en bouche, avec une finale gourmande, il gagne à être carafé pour révéler toute sa complexité. C’est le compagnon idéal des repas qui prennent leur temps, où la conversation coule aussi librement que le vin.",
      "price": "37.25$",
      "image_url": null,
      "link": null,
      "producer": "Sous le Végétal",
      "region": null,
      "vintage": "2022",
      "grape_varieties": null,
      "alcohol_content": null,
      "volume": null,
      "disponibilite": "SAQ",
      "all_occurrences_raw_data": [
        {
          "name": "Livia 2022",
          "description": "Pour un blanc vibrant d’émotion, Livia 2022, du projet Sous le Végétal, nous emmène sur l’île de Samos. Muscat salin et minéral, il conjugue profondeur, ampleur et élégance. Long en bouche, avec une finale gourmande, il gagne à être carafé pour révéler toute sa complexité. C’est le compagnon idéal des repas qui prennent leur temps, où la conversation coule aussi librement que le vin.",
          "price": "37.25$",
          "image_url": null,
          "link": null,
          "producer": "Sous le Végétal",
          "region": null,
          "vintage": "2022",
          "grape_varieties": null,
          "alcohol_content": null,
          "volume": null,
          "disponibilite": "SAQ"
        }
      ],
      "agence_was_defaulted": false
    },
    "summary": "Livia 2022, un Muscat de Samos, allie profondeur, ampleur et élégance, avec une finale gourmande qui s'épanouit après carafage, parfait pour des repas conviviaux."
  },
  {
    "id": "file-2025-08-30-le-vin-dans-les-voiles-0.html-chablis-2022",
    "blockId": "file-2025-08-30-le-vin-dans-les-voiles-0.html",
    "createdAt": "2025-08-30T00:00:00.000Z",
    "name": "Chablis 2022",
    "description": "Enfin, impossible de passer sous silence la noblesse de Chablis Duplessis 2022. Issu de parcelles face au Premier Cru Vaillons, ce vin droit et précis incarne l’élégance bourguignonne. Floral, minéral et doté d’un beau potentiel de garde, il s’accorde aussi bien aux apéros raffinés qu’aux plateaux de fruits de mer. Une valeur sûre qui apporte un accent d’élégance à toute tablée.",
    "price": "53.75$",
    "image_url": null,
    "link": null,
    "agence": "Le vin dans les voiles",
    "disponibilite": "SAQ",
    "raw_data": {
      "name": "Chablis 2022",
      "description": "Enfin, impossible de passer sous silence la noblesse de Chablis Duplessis 2022. Issu de parcelles face au Premier Cru Vaillons, ce vin droit et précis incarne l’élégance bourguignonne. Floral, minéral et doté d’un beau potentiel de garde, il s’accorde aussi bien aux apéros raffinés qu’aux plateaux de fruits de mer. Une valeur sûre qui apporte un accent d’élégance à toute tablée.",
      "price": "53.75$",
      "image_url": null,
      "link": null,
      "producer": "Caves Duplessis",
      "region": null,
      "vintage": "2022",
      "grape_varieties": null,
      "alcohol_content": null,
      "volume": null,
      "disponibilite": "SAQ",
      "all_occurrences_raw_data": [
        {
          "name": "Chablis 2022",
          "description": "Enfin, impossible de passer sous silence la noblesse de Chablis Duplessis 2022. Issu de parcelles face au Premier Cru Vaillons, ce vin droit et précis incarne l’élégance bourguignonne. Floral, minéral et doté d’un beau potentiel de garde, il s’accorde aussi bien aux apéros raffinés qu’aux plateaux de fruits de mer. Une valeur sûre qui apporte un accent d’élégance à toute tablée.",
          "price": "53.75$",
          "image_url": null,
          "link": null,
          "producer": "Caves Duplessis",
          "region": null,
          "vintage": "2022",
          "grape_varieties": null,
          "alcohol_content": null,
          "volume": null,
          "disponibilite": "SAQ"
        }
      ],
      "agence_was_defaulted": false
    },
    "summary": "Chablis Duplessis 2022, issu de parcelles face au Premier Cru Vaillons, incarne l’élégance bourguignonne avec ses notes florales et minérales, promettant un beau potentiel de garde."
  },
  {
    "id": "file-2025-08-29-noble-selection-0.html-pirate-of-cocoa-hill-2022",
    "blockId": "file-2025-08-29-noble-selection-0.html",
    "createdAt": "2025-08-29T00:00:00.000Z",
    "name": "Pirate of Cocoa Hill 2022",
    "description": "The Cocoa Hill Red 2022 est issu de vignes cultivées sur les sols granitiques décomposés de Cocoa Hill, une colline nichée au cœur des replis de la montagne de Stellenbosch. Les vignes bénéficient d'une grande exposition au soleil, ce qui permet aux raisins d'atteindre leur plein potentiel et de faire ressortir la richesse aromatique de chacun des cépages.",
    "price": "16,40$",
    "image_url": "https://dfalvymn23xg3.cloudfront.net/images/c_220x500_dornier-face-croped.png",
    "link": "https://nobleselection.us20.list-manage.com/track/click?u=3cbe129d9fba7fd6a0d135511&id=5f06566fcb&e=2c9a262afa",
    "agence": "Noble Sélection",
    "disponibilite": "SAQ",
    "raw_data": {
      "name": "Pirate of Cocoa Hill 2022",
      "description": "The Cocoa Hill Red 2022 est issu de vignes cultivées sur les sols granitiques décomposés de Cocoa Hill, une colline nichée au cœur des replis de la montagne de Stellenbosch. Les vignes bénéficient d'une grande exposition au soleil, ce qui permet aux raisins d'atteindre leur plein potentiel et de faire ressortir la richesse aromatique de chacun des cépages.",
      "price": "16,40$",
      "image_url": "https://dfalvymn23xg3.cloudfront.net/images/c_220x500_dornier-face-croped.png",
      "link": "https://nobleselection.us20.list-manage.com/track/click?u=3cbe129d9fba7fd6a0d135511&id=5f06566fcb&e=2c9a262afa",
      "producer": "Dornier",
      "region": "Western Cape",
      "vintage": "2022",
      "grape_varieties": [
        "Shiraz",
        "Merlot",
        "Cabernet Franc",
        "Tempranillo"
      ],
      "alcohol_content": "14%",
      "volume": null,
      "disponibilite": "SAQ",
      "all_occurrences_raw_data": [
        {
          "name": "Pirate of Cocoa Hill 2022",
          "description": "The Cocoa Hill Red 2022 est issu de vignes cultivées sur les sols granitiques décomposés de Cocoa Hill, une colline nichée au cœur des replis de la montagne de Stellenbosch. Les vignes bénéficient d'une grande exposition au soleil, ce qui permet aux raisins d'atteindre leur plein potentiel et de faire ressortir la richesse aromatique de chacun des cépages.",
          "price": "16,40$",
          "image_url": "https://dfalvymn23xg3.cloudfront.net/images/c_220x500_dornier-face-croped.png",
          "link": "https://nobleselection.us20.list-manage.com/track/click?u=3cbe129d9fba7fd6a0d135511&id=5f06566fcb&e=2c9a262afa",
          "producer": "Dornier",
          "region": "Western Cape",
          "vintage": "2022",
          "grape_varieties": [
            "Shiraz",
            "Merlot",
            "Cabernet Franc",
            "Tempranillo"
          ],
          "alcohol_content": "14%",
          "volume": null,
          "disponibilite": "SAQ"
        }
      ],
      "agence_was_defaulted": false
    },
    "summary": "Cocoa Hill Red 2022, cultivé sur des sols granitiques ensoleillés de Stellenbosch, révèle une richesse aromatique exceptionnelle grâce à l'exposition optimale de ses vignes."
  },
  {
    "id": "file-2025-08-29-noble-selection-0.html-bottega-white-gold",
    "blockId": "file-2025-08-29-noble-selection-0.html",
    "createdAt": "2025-08-29T00:00:00.000Z",
    "name": "Bottega White Gold",
    "description": null,
    "price": "31,00$",
    "image_url": "https://dfalvymn23xg3.cloudfront.net/images/c_220x500_13106568-1_1581313820.png",
    "link": "https://nobleselection.us20.list-manage.com/track/click?u=3cbe129d9fba7fd6a0d135511&id=02c5b91fc6&e=2c9a262afa",
    "agence": "Noble Sélection",
    "disponibilite": null,
    "raw_data": {
      "name": "Bottega White Gold",
      "description": null,
      "price": "31,00$",
      "image_url": "https://dfalvymn23xg3.cloudfront.net/images/c_220x500_13106568-1_1581313820.png",
      "link": "https://nobleselection.us20.list-manage.com/track/click?u=3cbe129d9fba7fd6a0d135511&id=02c5b91fc6&e=2c9a262afa",
      "producer": "Bottega",
      "region": null,
      "vintage": null,
      "grape_varieties": null,
      "alcohol_content": null,
      "volume": null,
      "disponibilite": null,
      "all_occurrences_raw_data": [
        {
          "name": "Bottega White Gold",
          "description": null,
          "price": "31,00$",
          "image_url": "https://dfalvymn23xg3.cloudfront.net/images/c_220x500_13106568-1_1581313820.png",
          "link": "https://nobleselection.us20.list-manage.com/track/click?u=3cbe129d9fba7fd6a0d135511&id=02c5b91fc6&e=2c9a262afa",
          "producer": "Bottega",
          "region": null,
          "vintage": null,
          "grape_varieties": null,
          "alcohol_content": null,
          "volume": null,
          "disponibilite": null
        }
      ],
      "agence_was_defaulted": false
    }
  },
  {
    "id": "file-2025-08-29-noble-selection-0.html-okendo-txakolina-astobiza-2022",
    "blockId": "file-2025-08-29-noble-selection-0.html",
    "createdAt": "2025-08-29T00:00:00.000Z",
    "name": "Okendo Txakolina Astobiza 2022",
    "description": null,
    "price": "22,50$",
    "image_url": "https://dfalvymn23xg3.cloudfront.net/images/c_220x500_astobiza-14250756-1_1578554716.png",
    "link": "https://nobleselection.us20.list-manage.com/track/click?u=3cbe129d9fba7fd6a0d135511&id=fbd5b0f155&e=2c9a262afa",
    "agence": "Noble Sélection",
    "disponibilite": null,
    "raw_data": {
      "name": "Okendo Txakolina Astobiza 2022",
      "description": null,
      "price": "22,50$",
      "image_url": "https://dfalvymn23xg3.cloudfront.net/images/c_220x500_astobiza-14250756-1_1578554716.png",
      "link": "https://nobleselection.us20.list-manage.com/track/click?u=3cbe129d9fba7fd6a0d135511&id=fbd5b0f155&e=2c9a262afa",
      "producer": "Astobiza",
      "region": null,
      "vintage": "2022",
      "grape_varieties": null,
      "alcohol_content": null,
      "volume": null,
      "disponibilite": null,
      "all_occurrences_raw_data": [
        {
          "name": "Okendo Txakolina Astobiza 2022",
          "description": null,
          "price": "22,50$",
          "image_url": "https://dfalvymn23xg3.cloudfront.net/images/c_220x500_astobiza-14250756-1_1578554716.png",
          "link": "https://nobleselection.us20.list-manage.com/track/click?u=3cbe129d9fba7fd6a0d135511&id=fbd5b0f155&e=2c9a262afa",
          "producer": "Astobiza",
          "region": null,
          "vintage": "2022",
          "grape_varieties": null,
          "alcohol_content": null,
          "volume": null,
          "disponibilite": null
        }
      ],
      "agence_was_defaulted": false
    }
  },
  {
    "id": "file-2025-08-29-noble-selection-0.html-alba-de-vetus-rias-baixas-2024",
    "blockId": "file-2025-08-29-noble-selection-0.html",
    "createdAt": "2025-08-29T00:00:00.000Z",
    "name": "Alba de Vetus Rias Baixas 2024",
    "description": null,
    "price": "25,85$",
    "image_url": "https://dfalvymn23xg3.cloudfront.net/images/c_220x500_image1_75.png",
    "link": "https://nobleselection.us20.list-manage.com/track/click?u=3cbe129d9fba7fd6a0d135511&id=58bca3bd29&e=2c9a262afa",
    "agence": "Noble Sélection",
    "disponibilite": null,
    "raw_data": {
      "name": "Alba de Vetus Rias Baixas 2024",
      "description": null,
      "price": "25,85$",
      "image_url": "https://dfalvymn23xg3.cloudfront.net/images/c_220x500_image1_75.png",
      "link": "https://nobleselection.us20.list-manage.com/track/click?u=3cbe129d9fba7fd6a0d135511&id=58bca3bd29&e=2c9a262afa",
      "producer": "Vetus",
      "region": null,
      "vintage": "2024",
      "grape_varieties": null,
      "alcohol_content": null,
      "volume": null,
      "disponibilite": null,
      "all_occurrences_raw_data": [
        {
          "name": "Alba de Vetus Rias Baixas 2024",
          "description": null,
          "price": "25,85$",
          "image_url": "https://dfalvymn23xg3.cloudfront.net/images/c_220x500_image1_75.png",
          "link": "https://nobleselection.us20.list-manage.com/track/click?u=3cbe129d9fba7fd6a0d135511&id=58bca3bd29&e=2c9a262afa",
          "producer": "Vetus",
          "region": null,
          "vintage": "2024",
          "grape_varieties": null,
          "alcohol_content": null,
          "volume": null,
          "disponibilite": null
        }
      ],
      "agence_was_defaulted": false
    }
  },
  {
    "id": "file-2025-08-29-noble-selection-0.html-mas-elena-2020",
    "blockId": "file-2025-08-29-noble-selection-0.html",
    "createdAt": "2025-08-29T00:00:00.000Z",
    "name": "Mas Elena 2020",
    "description": null,
    "price": "21,95$",
    "image_url": "https://dfalvymn23xg3.cloudfront.net/images/c_220x500_mas-elena-2-copie.png",
    "link": "https://nobleselection.us20.list-manage.com/track/click?u=3cbe129d9fba7fd6a0d135511&id=ca01cc88b9&e=2c9a262afa",
    "agence": "Noble Sélection",
    "disponibilite": null,
    "raw_data": {
      "name": "Mas Elena 2020",
      "description": null,
      "price": "21,95$",
      "image_url": "https://dfalvymn23xg3.cloudfront.net/images/c_220x500_mas-elena-2-copie.png",
      "link": "https://nobleselection.us20.list-manage.com/track/click?u=3cbe129d9fba7fd6a0d135511&id=ca01cc88b9&e=2c9a262afa",
      "producer": "Parés Baltà",
      "region": null,
      "vintage": "2020",
      "grape_varieties": null,
      "alcohol_content": null,
      "volume": null,
      "disponibilite": null,
      "all_occurrences_raw_data": [
        {
          "name": "Mas Elena 2020",
          "description": null,
          "price": "21,95$",
          "image_url": "https://dfalvymn23xg3.cloudfront.net/images/c_220x500_mas-elena-2-copie.png",
          "link": "https://nobleselection.us20.list-manage.com/track/click?u=3cbe129d9fba7fd6a0d135511&id=ca01cc88b9&e=2c9a262afa",
          "producer": "Parés Baltà",
          "region": null,
          "vintage": "2020",
          "grape_varieties": null,
          "alcohol_content": null,
          "volume": null,
          "disponibilite": null
        }
      ],
      "agence_was_defaulted": false
    }
  },
  {
    "id": "file-2025-08-29-noble-selection-0.html-montresor-satinato-soave-biologico-2023",
    "blockId": "file-2025-08-29-noble-selection-0.html",
    "createdAt": "2025-08-29T00:00:00.000Z",
    "name": "Montresor Satinato Soave Biologico 2023",
    "description": null,
    "price": "19,95$",
    "image_url": "https://dfalvymn23xg3.cloudfront.net/images/c_220x500_satinato-montresor-.png",
    "link": "https://nobleselection.us20.list-manage.com/track/click?u=3cbe129d9fba7fd6a0d135511&id=f1da17d0b8&e=2c9a262afa",
    "agence": "Noble Sélection",
    "disponibilite": null,
    "raw_data": {
      "name": "Montresor Satinato Soave Biologico 2023",
      "description": null,
      "price": "19,95$",
      "image_url": "https://dfalvymn23xg3.cloudfront.net/images/c_220x500_satinato-montresor-.png",
      "link": "https://nobleselection.us20.list-manage.com/track/click?u=3cbe129d9fba7fd6a0d135511&id=f1da17d0b8&e=2c9a262afa",
      "producer": "Montresor",
      "region": null,
      "vintage": "2023",
      "grape_varieties": null,
      "alcohol_content": null,
      "volume": null,
      "disponibilite": null,
      "all_occurrences_raw_data": [
        {
          "name": "Montresor Satinato Soave Biologico 2023",
          "description": null,
          "price": "19,95$",
          "image_url": "https://dfalvymn23xg3.cloudfront.net/images/c_220x500_satinato-montresor-.png",
          "link": "https://nobleselection.us20.list-manage.com/track/click?u=3cbe129d9fba7fd6a0d135511&id=f1da17d0b8&e=2c9a262afa",
          "producer": "Montresor",
          "region": null,
          "vintage": "2023",
          "grape_varieties": null,
          "alcohol_content": null,
          "volume": null,
          "disponibilite": null
        }
      ],
      "agence_was_defaulted": false
    }
  },
  {
    "id": "file-2025-08-29-noble-selection-0.html-bourgogne-chardonnay-2023",
    "blockId": "file-2025-08-29-noble-selection-0.html",
    "createdAt": "2025-08-29T00:00:00.000Z",
    "name": "Bourgogne Chardonnay 2023",
    "description": null,
    "price": "26,70$",
    "image_url": "https://dfalvymn23xg3.cloudfront.net/images/c_220x500_jean-marc-brocard-bourgogne-chardonnay_2.png",
    "link": "https://nobleselection.us20.list-manage.com/track/click?u=3cbe129d9fba7fd6a0d135511&id=604a0b6dec&e=2c9a262afa",
    "agence": "Noble Sélection",
    "disponibilite": null,
    "raw_data": {
      "name": "Bourgogne Chardonnay 2023",
      "description": null,
      "price": "26,70$",
      "image_url": "https://dfalvymn23xg3.cloudfront.net/images/c_220x500_jean-marc-brocard-bourgogne-chardonnay_2.png",
      "link": "https://nobleselection.us20.list-manage.com/track/click?u=3cbe129d9fba7fd6a0d135511&id=604a0b6dec&e=2c9a262afa",
      "producer": "Jean-Marc Brocard",
      "region": null,
      "vintage": "2023",
      "grape_varieties": null,
      "alcohol_content": null,
      "volume": null,
      "disponibilite": null,
      "all_occurrences_raw_data": [
        {
          "name": "Bourgogne Chardonnay 2023",
          "description": null,
          "price": "26,70$",
          "image_url": "https://dfalvymn23xg3.cloudfront.net/images/c_220x500_jean-marc-brocard-bourgogne-chardonnay_2.png",
          "link": "https://nobleselection.us20.list-manage.com/track/click?u=3cbe129d9fba7fd6a0d135511&id=604a0b6dec&e=2c9a262afa",
          "producer": "Jean-Marc Brocard",
          "region": null,
          "vintage": "2023",
          "grape_varieties": null,
          "alcohol_content": null,
          "volume": null,
          "disponibilite": null
        }
      ],
      "agence_was_defaulted": false
    }
  },
  {
    "id": "file-2025-08-29-noble-selection-0.html-organic-dao-2019",
    "blockId": "file-2025-08-29-noble-selection-0.html",
    "createdAt": "2025-08-29T00:00:00.000Z",
    "name": "Organic Dão 2019",
    "description": null,
    "price": "18,90$",
    "image_url": "https://dfalvymn23xg3.cloudfront.net/images/c_220x500_cabriz-organic-daoe-2019.png",
    "link": "https://nobleselection.us20.list-manage.com/track/click?u=3cbe129d9fba7fd6a0d135511&id=bc42eec73d&e=2c9a262afa",
    "agence": "Noble Sélection",
    "disponibilite": null,
    "raw_data": {
      "name": "Organic Dão 2019",
      "description": null,
      "price": "18,90$",
      "image_url": "https://dfalvymn23xg3.cloudfront.net/images/c_220x500_cabriz-organic-daoe-2019.png",
      "link": "https://nobleselection.us20.list-manage.com/track/click?u=3cbe129d9fba7fd6a0d135511&id=bc42eec73d&e=2c9a262afa",
      "producer": "Global Wines",
      "region": null,
      "vintage": "2019",
      "grape_varieties": null,
      "alcohol_content": null,
      "volume": null,
      "disponibilite": null,
      "all_occurrences_raw_data": [
        {
          "name": "Organic Dão 2019",
          "description": null,
          "price": "18,90$",
          "image_url": "https://dfalvymn23xg3.cloudfront.net/images/c_220x500_cabriz-organic-daoe-2019.png",
          "link": "https://nobleselection.us20.list-manage.com/track/click?u=3cbe129d9fba7fd6a0d135511&id=bc42eec73d&e=2c9a262afa",
          "producer": "Global Wines",
          "region": null,
          "vintage": "2019",
          "grape_varieties": null,
          "alcohol_content": null,
          "volume": null,
          "disponibilite": null
        }
      ],
      "agence_was_defaulted": false
    }
  },
  {
    "id": "file-2025-08-29-noble-selection-0.html-cascina-valle-asinari-ciuchino-2022",
    "blockId": "file-2025-08-29-noble-selection-0.html",
    "createdAt": "2025-08-29T00:00:00.000Z",
    "name": "Cascina Valle Asinari Ciuchino 2022",
    "description": null,
    "price": "24,55$",
    "image_url": "https://dfalvymn23xg3.cloudfront.net/images/c_220x500_cascina-asinari-ciuchino_4.png",
    "link": "https://nobleselection.us20.list-manage.com/track/click?u=3cbe129d9fba7fd6a0d135511&id=cbf62c67cc&e=2c9a262afa",
    "agence": "Noble Sélection",
    "disponibilite": null,
    "raw_data": {
      "name": "Cascina Valle Asinari Ciuchino 2022",
      "description": null,
      "price": "24,55$",
      "image_url": "https://dfalvymn23xg3.cloudfront.net/images/c_220x500_cascina-asinari-ciuchino_4.png",
      "link": "https://nobleselection.us20.list-manage.com/track/click?u=3cbe129d9fba7fd6a0d135511&id=cbf62c67cc&e=2c9a262afa",
      "producer": "Cascina Valle Asinari",
      "region": null,
      "vintage": "2022",
      "grape_varieties": null,
      "alcohol_content": null,
      "volume": null,
      "disponibilite": null,
      "all_occurrences_raw_data": [
        {
          "name": "Cascina Valle Asinari Ciuchino 2022",
          "description": null,
          "price": "24,55$",
          "image_url": "https://dfalvymn23xg3.cloudfront.net/images/c_220x500_cascina-asinari-ciuchino_4.png",
          "link": "https://nobleselection.us20.list-manage.com/track/click?u=3cbe129d9fba7fd6a0d135511&id=cbf62c67cc&e=2c9a262afa",
          "producer": "Cascina Valle Asinari",
          "region": null,
          "vintage": "2022",
          "grape_varieties": null,
          "alcohol_content": null,
          "volume": null,
          "disponibilite": null
        }
      ],
      "agence_was_defaulted": false
    }
  },
  {
    "id": "file-2025-08-29-vin-dame-jeanne-0.html-riesling-cote-de-rouffach",
    "blockId": "file-2025-08-29-vin-dame-jeanne-0.html",
    "createdAt": "2025-08-29T00:00:00.000Z",
    "name": "Riesling 'Cote de Rouffach'",
    "description": "Depuis 2005, l'appellation Côte de Rouffach est reconnue pour son caractère unique. Délicat, sec, et soyeux, le Riesling 2023 est issu de vignes de 45 ans en biodynamie sur argiles et calcaires jaunes. 18 mois d'élevage sur lies fines. Complètement sec, tendu, et salivant. Quelle belle bouteille!",
    "price": "35.25$",
    "image_url": "https://gallery.mailchimp.com/0711127c320d32e15ce6dc05f/images/adf2b9d7-739a-4c47-bfb0-d1c357915531.jpg",
    "link": "https://vindamejeanne.us10.list-manage.com/track/click?u=0711127c320d32e15ce6dc05f&id=3af50f4aa7&e=345e10d07b",
    "agence": "Vin Dame-Jeanne",
    "disponibilite": "SAQ",
    "raw_data": {
      "name": "Riesling 'Cote de Rouffach'",
      "description": "Depuis 2005, l'appellation Côte de Rouffach est reconnue pour son caractère unique. Délicat, sec, et soyeux, le Riesling 2023 est issu de vignes de 45 ans en biodynamie sur argiles et calcaires jaunes. 18 mois d'élevage sur lies fines. Complètement sec, tendu, et salivant. Quelle belle bouteille!",
      "price": "35.25$",
      "image_url": "https://gallery.mailchimp.com/0711127c320d32e15ce6dc05f/images/adf2b9d7-739a-4c47-bfb0-d1c357915531.jpg",
      "link": "https://vindamejeanne.us10.list-manage.com/track/click?u=0711127c320d32e15ce6dc05f&id=3af50f4aa7&e=345e10d07b",
      "producer": "Véronique et Thomas Muré",
      "region": "Côte de Rouffach",
      "vintage": "2023",
      "grape_varieties": null,
      "alcohol_content": null,
      "volume": null,
      "disponibilite": "SAQ",
      "all_occurrences_raw_data": [
        {
          "name": "Riesling 'Cote de Rouffach'",
          "description": "Depuis 2005, l'appellation Côte de Rouffach est reconnue pour son caractère unique. Délicat, sec, et soyeux, le Riesling 2023 est issu de vignes de 45 ans en biodynamie sur argiles et calcaires jaunes. 18 mois d'élevage sur lies fines. Complètement sec, tendu, et salivant. Quelle belle bouteille!",
          "price": "35.25$",
          "image_url": "https://gallery.mailchimp.com/0711127c320d32e15ce6dc05f/images/adf2b9d7-739a-4c47-bfb0-d1c357915531.jpg",
          "link": "https://vindamejeanne.us10.list-manage.com/track/click?u=0711127c320d32e15ce6dc05f&id=3af50f4aa7&e=345e10d07b",
          "producer": "Véronique et Thomas Muré",
          "region": "Côte de Rouffach",
          "vintage": "2023",
          "grape_varieties": null,
          "alcohol_content": null,
          "volume": null,
          "disponibilite": "SAQ"
        }
      ],
      "agence_was_defaulted": false
    },
    "summary": "Le Riesling 2023 de Côte de Rouffach, délicat et soyeux, est un vin biodynamique, sec et tendu, offrant une belle salinité après 18 mois d'élevage sur lies fines."
  },
  {
    "id": "file-2025-08-29-vin-dame-jeanne-0.html-riesling-grand-cru-vorbourg-clos-saint-landelin",
    "blockId": "file-2025-08-29-vin-dame-jeanne-0.html",
    "createdAt": "2025-08-29T00:00:00.000Z",
    "name": "Riesling, Grand Cru Vorbourg, Clos Saint Landelin",
    "description": "L'emblématique Clos Saint Landelin, Monopole familial chez Muré, constitue l'extrémité sud du Grand Cru Vorbourg, exposé plein sud avec des vents du nord-ouest. Vignes de 50 ans plantées en haute-densité, sur pentes abruptes en terrasses, sur des sols marno-calcaires avec beaucoup de cailloux. Puissance surprenante ici, vif, avec une grande sensation crayeuse. Riesling de gastronomie, hyper sec et citronné, concentré et chargé de matière. Potentiel de garde énorme.",
    "price": "66.50$",
    "image_url": "https://gallery.mailchimp.com/0711127c320d32e15ce6dc05f/images/adf2b9d7-739a-4c47-bfb0-d1c357915531.jpg",
    "link": "https://vindamejeanne.us10.list-manage.com/track/click?u=0711127c320d32e15ce6dc05f&id=3af50f4aa7&e=345e10d07b",
    "agence": "Vin Dame-Jeanne",
    "disponibilite": "SAQ",
    "raw_data": {
      "name": "Riesling, Grand Cru Vorbourg, Clos Saint Landelin",
      "description": "L'emblématique Clos Saint Landelin, Monopole familial chez Muré, constitue l'extrémité sud du Grand Cru Vorbourg, exposé plein sud avec des vents du nord-ouest. Vignes de 50 ans plantées en haute-densité, sur pentes abruptes en terrasses, sur des sols marno-calcaires avec beaucoup de cailloux. Puissance surprenante ici, vif, avec une grande sensation crayeuse. Riesling de gastronomie, hyper sec et citronné, concentré et chargé de matière. Potentiel de garde énorme.",
      "price": "66.50$",
      "image_url": "https://gallery.mailchimp.com/0711127c320d32e15ce6dc05f/images/adf2b9d7-739a-4c47-bfb0-d1c357915531.jpg",
      "link": "https://vindamejeanne.us10.list-manage.com/track/click?u=0711127c320d32e15ce6dc05f&id=3af50f4aa7&e=345e10d07b",
      "producer": "Véronique et Thomas Muré",
      "region": "Grand Cru Vorbourg",
      "vintage": "2020",
      "grape_varieties": null,
      "alcohol_content": null,
      "volume": null,
      "disponibilite": "SAQ",
      "all_occurrences_raw_data": [
        {
          "name": "Riesling, Grand Cru Vorbourg, Clos Saint Landelin",
          "description": "L'emblématique Clos Saint Landelin, Monopole familial chez Muré, constitue l'extrémité sud du Grand Cru Vorbourg, exposé plein sud avec des vents du nord-ouest. Vignes de 50 ans plantées en haute-densité, sur pentes abruptes en terrasses, sur des sols marno-calcaires avec beaucoup de cailloux. Puissance surprenante ici, vif, avec une grande sensation crayeuse. Riesling de gastronomie, hyper sec et citronné, concentré et chargé de matière. Potentiel de garde énorme.",
          "price": "66.50$",
          "image_url": "https://gallery.mailchimp.com/0711127c320d32e15ce6dc05f/images/adf2b9d7-739a-4c47-bfb0-d1c357915531.jpg",
          "link": "https://vindamejeanne.us10.list-manage.com/track/click?u=0711127c320d32e15ce6dc05f&id=3af50f4aa7&e=345e10d07b",
          "producer": "Véronique et Thomas Muré",
          "region": "Grand Cru Vorbourg",
          "vintage": "2020",
          "grape_varieties": null,
          "alcohol_content": null,
          "volume": null,
          "disponibilite": "SAQ"
        }
      ],
      "agence_was_defaulted": false
    },
    "summary": "Le Riesling du Clos Saint Landelin, issu de vignes de 50 ans sur des pentes abruptes, offre une puissance vive et une sensation crayeuse, promettant une grande longévité."
  },
  {
    "id": "file-2025-08-28-bambara-selection-0.html-pastis-de-la-plaine",
    "blockId": "file-2025-08-28-bambara-selection-0.html",
    "createdAt": "2025-08-28T00:00:00.000Z",
    "name": "Pastis de la Plaine",
    "description": "Jusqu’ici, nous avions proposé différents spiritueux artisanaux en importation privée. Aujourd’hui, une nouvelle étape s’ouvre avec la Distillerie de la Plaine : notre tout premier pastis, et pas n’importe lequel — le seul pastis bio sur les tablettes!!🌱 En exclusivité en ligne sur SAQ.com maintenant! Voici le tout premier pastis de notre gamme, et il porte haut les couleurs de Marseille! Conçu en petite série par Guillaume Strebler fondateur de la Distillerie de la Plaine, ce pastis est avant tout une histoire d’artisanat et de conviction. Pas d’artifice, pas de compromis : uniquement des ingrédients bio et des plantes sélectionnées à la mythique Herboristerie du Père Blaize, une véritable institution marseillaise depuis 1815. Le résultat est un pastis d’une qualité incomparable, qui sort clairement du lot! L’anis étoilé et la réglisse posent les bases, fidèles aux traditions, mais c’est le fenouil de Provence qui fait toute la différence. Une touche inattendue qui apporte fraîcheur, relief et une personnalité unique. Ce n’est ni un simple anisé, ni une copie des standards industriels : c’est un pastis radicalement marseillais, mais avec une signature audacieuse bien à lui. En bouche, on retrouve un équilibre parfait : l’intensité aromatique de l’anis, la rondeur de la réglisse, la vivacité du fenouil. La robe blanche une fois diluée annonce un profil fin, net et franc, qui séduit aussi bien les amoureux de longue date que les curieux prêts à redécouvrir l’anisé autrement. Un pastis de caractère, artisanal, biologique et méditerranéen. Conseil de service : versez une part de Pastis de la Plaine dans un grand verre, et ajoutez cinq parts d’eau et 2 glaçons. Rien de plus, rien de moins. L’authentique rituel marseillais! À déguster en apéritif bien sûr, mais aussi à table avec des poissons grillés, une cuisine méditerranéenne ensoleillée ou même quelques fromages frais. Sans oublier les moments conviviaux : au soleil, en jouant à la pétanque ou lors d’un dimanche entre amis au chalet – exactement comme il se doit à Marseille ! Une première qui ne laisse personne indifférent, et qui a tout pour devenir un nouveau classique! Attention, les quantités sont très limitées!! Santé!!",
    "price": "67,75 $",
    "image_url": "https://mcusercontent.com/d2f1e39952eafd8949f464f3f/_compresseds/0bff07fa-e59d-3b48-47f6-33e91e4d7ff3.jpg",
    "link": "https://bambaraselection.us1.list-manage.com/track/click?u=d2f1e39952eafd8949f464f3f&id=cd7bd0e3f7&e=a09c2580fc",
    "agence": "Bambara Selection",
    "disponibilite": "SAQ",
    "raw_data": {
      "name": "Pastis de la Plaine",
      "description": "Jusqu’ici, nous avions proposé différents spiritueux artisanaux en importation privée. Aujourd’hui, une nouvelle étape s’ouvre avec la Distillerie de la Plaine : notre tout premier pastis, et pas n’importe lequel — le seul pastis bio sur les tablettes!!🌱 En exclusivité en ligne sur SAQ.com maintenant! Voici le tout premier pastis de notre gamme, et il porte haut les couleurs de Marseille! Conçu en petite série par Guillaume Strebler fondateur de la Distillerie de la Plaine, ce pastis est avant tout une histoire d’artisanat et de conviction. Pas d’artifice, pas de compromis : uniquement des ingrédients bio et des plantes sélectionnées à la mythique Herboristerie du Père Blaize, une véritable institution marseillaise depuis 1815. Le résultat est un pastis d’une qualité incomparable, qui sort clairement du lot! L’anis étoilé et la réglisse posent les bases, fidèles aux traditions, mais c’est le fenouil de Provence qui fait toute la différence. Une touche inattendue qui apporte fraîcheur, relief et une personnalité unique. Ce n’est ni un simple anisé, ni une copie des standards industriels : c’est un pastis radicalement marseillais, mais avec une signature audacieuse bien à lui. En bouche, on retrouve un équilibre parfait : l’intensité aromatique de l’anis, la rondeur de la réglisse, la vivacité du fenouil. La robe blanche une fois diluée annonce un profil fin, net et franc, qui séduit aussi bien les amoureux de longue date que les curieux prêts à redécouvrir l’anisé autrement. Un pastis de caractère, artisanal, biologique et méditerranéen. Conseil de service : versez une part de Pastis de la Plaine dans un grand verre, et ajoutez cinq parts d’eau et 2 glaçons. Rien de plus, rien de moins. L’authentique rituel marseillais! À déguster en apéritif bien sûr, mais aussi à table avec des poissons grillés, une cuisine méditerranéenne ensoleillée ou même quelques fromages frais. Sans oublier les moments conviviaux : au soleil, en jouant à la pétanque ou lors d’un dimanche entre amis au chalet – exactement comme il se doit à Marseille ! Une première qui ne laisse personne indifférent, et qui a tout pour devenir un nouveau classique! Attention, les quantités sont très limitées!! Santé!!",
      "price": "67,75 $",
      "image_url": "https://mcusercontent.com/d2f1e39952eafd8949f464f3f/_compresseds/0bff07fa-e59d-3b48-47f6-33e91e4d7ff3.jpg",
      "link": "https://bambaraselection.us1.list-manage.com/track/click?u=d2f1e39952eafd8949f464f3f&id=cd7bd0e3f7&e=a09c2580fc",
      "producer": "Distillerie de la Plaine",
      "region": "Marseille",
      "vintage": null,
      "grape_varieties": null,
      "alcohol_content": null,
      "volume": null,
      "disponibilite": "SAQ",
      "all_occurrences_raw_data": [
        {
          "name": "Pastis de la Plaine",
          "description": "Jusqu’ici, nous avions proposé différents spiritueux artisanaux en importation privée. Aujourd’hui, une nouvelle étape s’ouvre avec la Distillerie de la Plaine : notre tout premier pastis, et pas n’importe lequel — le seul pastis bio sur les tablettes!!🌱 En exclusivité en ligne sur SAQ.com maintenant! Voici le tout premier pastis de notre gamme, et il porte haut les couleurs de Marseille! Conçu en petite série par Guillaume Strebler fondateur de la Distillerie de la Plaine, ce pastis est avant tout une histoire d’artisanat et de conviction. Pas d’artifice, pas de compromis : uniquement des ingrédients bio et des plantes sélectionnées à la mythique Herboristerie du Père Blaize, une véritable institution marseillaise depuis 1815. Le résultat est un pastis d’une qualité incomparable, qui sort clairement du lot! L’anis étoilé et la réglisse posent les bases, fidèles aux traditions, mais c’est le fenouil de Provence qui fait toute la différence. Une touche inattendue qui apporte fraîcheur, relief et une personnalité unique. Ce n’est ni un simple anisé, ni une copie des standards industriels : c’est un pastis radicalement marseillais, mais avec une signature audacieuse bien à lui. En bouche, on retrouve un équilibre parfait : l’intensité aromatique de l’anis, la rondeur de la réglisse, la vivacité du fenouil. La robe blanche une fois diluée annonce un profil fin, net et franc, qui séduit aussi bien les amoureux de longue date que les curieux prêts à redécouvrir l’anisé autrement. Un pastis de caractère, artisanal, biologique et méditerranéen. Conseil de service : versez une part de Pastis de la Plaine dans un grand verre, et ajoutez cinq parts d’eau et 2 glaçons. Rien de plus, rien de moins. L’authentique rituel marseillais! À déguster en apéritif bien sûr, mais aussi à table avec des poissons grillés, une cuisine méditerranéenne ensoleillée ou même quelques fromages frais. Sans oublier les moments conviviaux : au soleil, en jouant à la pétanque ou lors d’un dimanche entre amis au chalet – exactement comme il se doit à Marseille ! Une première qui ne laisse personne indifférent, et qui a tout pour devenir un nouveau classique! Attention, les quantités sont très limitées!! Santé!!",
          "price": "67,75 $",
          "image_url": "https://mcusercontent.com/d2f1e39952eafd8949f464f3f/_compresseds/0bff07fa-e59d-3b48-47f6-33e91e4d7ff3.jpg",
          "link": "https://bambaraselection.us1.list-manage.com/track/click?u=d2f1e39952eafd8949f464f3f&id=cd7bd0e3f7&e=a09c2580fc",
          "producer": "Distillerie de la Plaine",
          "region": "Marseille",
          "vintage": null,
          "grape_varieties": null,
          "alcohol_content": null,
          "volume": null,
          "disponibilite": "SAQ"
        }
      ],
      "agence_was_defaulted": false
    },
    "summary": "Le Pastis de la Plaine, premier pastis bio, incarne l'artisanat marseillais avec des ingrédients sélectionnés, offrant une fraîcheur unique grâce à l'anis étoilé, la réglisse et le fenouil de Provence."
  },
  {
    "id": "file-2025-08-28-bambara-selection-0.html-gulfi-valcanzjria-2023",
    "blockId": "file-2025-08-28-bambara-selection-0.html",
    "createdAt": "2025-08-28T00:00:00.000Z",
    "name": "Gulfi, Valcanzjria 2023",
    "description": "Valcanzjria, le premier vin blanc de Gulfi à la SAQ, est enfin de retour! Valcanjzria est un assemblage de chardonnay et de carricante, ce dernier étant un cépage autochtone à la Sicile. Situé à 400 mètres d’altitude sur des sols calcaires, le vignoble biologique et non irrigué subit de grandes variations climatiques entre le jour et la nuit ce qui encourage le développement optimal des arômes et le maintien d’un taux d’acidité élevé. Le chardonnay donne une richesse aromatique au vin et apporte de la rondeur et le carricante apporte une belle acidité et de la complexité; il est en quelque sorte la colonne vertébrale qui permet au vin d’évoluer au fil du temps et de conserver sa fraîcheur et son intensité aromatique. Cette cuvée dévoile un profil aromatique de pomme, melon et fruits tropicaux délicats, auquel se greffent l’amande et le miel. En bouche, le vin dévoile toute sa personnalité avec un équilibre remarquable entre la richesse du fruit et la matière saline. Le vin ne fait aucun passage en bois afin de laisser transparaître toute la pureté des cépages et du terroir. Cette cuvée s'accordera parfaitement aux crustacés tels que le crabe et les crevettes, au poisson, au risotto et aux plats frais de légumes! Santé!",
    "price": "31,00 $",
    "image_url": null,
    "link": "https://bambaraselection.us1.list-manage.com/track/click?u=d2f1e39952eafd8949f464f3f&id=45a309f128&e=a09c2580fc",
    "agence": "Bambara Selection",
    "disponibilite": "SAQ",
    "raw_data": {
      "name": "Gulfi, Valcanzjria 2023",
      "description": "Valcanzjria, le premier vin blanc de Gulfi à la SAQ, est enfin de retour! Valcanjzria est un assemblage de chardonnay et de carricante, ce dernier étant un cépage autochtone à la Sicile. Situé à 400 mètres d’altitude sur des sols calcaires, le vignoble biologique et non irrigué subit de grandes variations climatiques entre le jour et la nuit ce qui encourage le développement optimal des arômes et le maintien d’un taux d’acidité élevé. Le chardonnay donne une richesse aromatique au vin et apporte de la rondeur et le carricante apporte une belle acidité et de la complexité; il est en quelque sorte la colonne vertébrale qui permet au vin d’évoluer au fil du temps et de conserver sa fraîcheur et son intensité aromatique. Cette cuvée dévoile un profil aromatique de pomme, melon et fruits tropicaux délicats, auquel se greffent l’amande et le miel. En bouche, le vin dévoile toute sa personnalité avec un équilibre remarquable entre la richesse du fruit et la matière saline. Le vin ne fait aucun passage en bois afin de laisser transparaître toute la pureté des cépages et du terroir. Cette cuvée s'accordera parfaitement aux crustacés tels que le crabe et les crevettes, au poisson, au risotto et aux plats frais de légumes! Santé!",
      "price": "31,00 $",
      "image_url": null,
      "link": "https://bambaraselection.us1.list-manage.com/track/click?u=d2f1e39952eafd8949f464f3f&id=45a309f128&e=a09c2580fc",
      "producer": "Gulfi",
      "region": "Sicile",
      "vintage": "2023",
      "grape_varieties": [
        "Chardonnay",
        "Carricante"
      ],
      "alcohol_content": "Biologique",
      "volume": null,
      "disponibilite": "SAQ",
      "all_occurrences_raw_data": [
        {
          "name": "Gulfi, Valcanzjria 2023",
          "description": "Valcanzjria, le premier vin blanc de Gulfi à la SAQ, est enfin de retour! Valcanjzria est un assemblage de chardonnay et de carricante, ce dernier étant un cépage autochtone à la Sicile. Situé à 400 mètres d’altitude sur des sols calcaires, le vignoble biologique et non irrigué subit de grandes variations climatiques entre le jour et la nuit ce qui encourage le développement optimal des arômes et le maintien d’un taux d’acidité élevé. Le chardonnay donne une richesse aromatique au vin et apporte de la rondeur et le carricante apporte une belle acidité et de la complexité; il est en quelque sorte la colonne vertébrale qui permet au vin d’évoluer au fil du temps et de conserver sa fraîcheur et son intensité aromatique. Cette cuvée dévoile un profil aromatique de pomme, melon et fruits tropicaux délicats, auquel se greffent l’amande et le miel. En bouche, le vin dévoile toute sa personnalité avec un équilibre remarquable entre la richesse du fruit et la matière saline. Le vin ne fait aucun passage en bois afin de laisser transparaître toute la pureté des cépages et du terroir. Cette cuvée s'accordera parfaitement aux crustacés tels que le crabe et les crevettes, au poisson, au risotto et aux plats frais de légumes! Santé!",
          "price": "31,00 $",
          "image_url": null,
          "link": "https://bambaraselection.us1.list-manage.com/track/click?u=d2f1e39952eafd8949f464f3f&id=45a309f128&e=a09c2580fc",
          "producer": "Gulfi",
          "region": "Sicile",
          "vintage": "2023",
          "grape_varieties": [
            "Chardonnay",
            "Carricante"
          ],
          "alcohol_content": "Biologique",
          "volume": null,
          "disponibilite": "SAQ"
        }
      ],
      "agence_was_defaulted": false
    },
    "summary": "Valcanzjria, assemblage de Chardonnay et Carricante, offre une richesse aromatique de fruits tropicaux et une belle salinité, révélant la pureté de son terroir sicilien sans passage en bois."
  },
  {
    "id": "file-2025-08-28-bambara-selection-0.html-paso-a-paso-criollas-clarete-2024",
    "blockId": "file-2025-08-28-bambara-selection-0.html",
    "createdAt": "2025-08-28T00:00:00.000Z",
    "name": "Paso a Paso, Criollas Clarete 2024",
    "description": "Un vin unique à découvrir, en exclusivité SAQ.com dès maintenant!! Découvrez le Clarete de Paso a Paso, une nouvelle expression du Clarete, ce vin argentin entre un rosé et un rouge léger, typique et rafraîchissant, élaboré à partir de cépages autochtones Criollas! Ce vin est l'incarnation parfaite du style authentique et traditionnel apprécié par plusieurs générations d'Argentins dans leur vie quotidienne. Ce Clarete, majoritairement composé de Criolla rouge avec une touche de Criolla blanc, est issu de vieilles vignes de 80 ans cultivées sans pesticides dans un sol argileux profond. Le pressurage doux préserve l'intégrité des baies, suivi d'une fermentation spontanée en cuves inox avec des levures indigènes. Une petite partie subit une fermentation malolactique. Sans ajout de sulfites ni filtration, ce vin n'est pas vieilli en fûts de bois pour conserver sa fraîcheur caractéristique, offrant un Clarete doux et facile à boire. Les notes de dégustation révèlent un vin sur le fruit, avec des arômes floraux et minéraux. En bouche, il se distingue par sa superbe fraîcheur, une acidité équilibrée et une belle intensité. À servir bien frais, ce vin unique est idéal pour être savouré au bord de la piscine par une journée ensoleillée! Il s'accorde parfaitement avec une salade de roquette, de la betterave, avec des poissons ainsi qu'avec des fruits de mer et une paella. Une superbe découverte au prix doux!!",
    "price": "20,05 $",
    "image_url": null,
    "link": "https://bambaraselection.us1.list-manage.com/track/click?u=d2f1e39952eafd8949f464f3f&id=6c7d679ff0&e=a09c2580fc",
    "agence": "Bambara Selection",
    "disponibilite": "SAQ",
    "raw_data": {
      "name": "Paso a Paso, Criollas Clarete 2024",
      "description": "Un vin unique à découvrir, en exclusivité SAQ.com dès maintenant!! Découvrez le Clarete de Paso a Paso, une nouvelle expression du Clarete, ce vin argentin entre un rosé et un rouge léger, typique et rafraîchissant, élaboré à partir de cépages autochtones Criollas! Ce vin est l'incarnation parfaite du style authentique et traditionnel apprécié par plusieurs générations d'Argentins dans leur vie quotidienne. Ce Clarete, majoritairement composé de Criolla rouge avec une touche de Criolla blanc, est issu de vieilles vignes de 80 ans cultivées sans pesticides dans un sol argileux profond. Le pressurage doux préserve l'intégrité des baies, suivi d'une fermentation spontanée en cuves inox avec des levures indigènes. Une petite partie subit une fermentation malolactique. Sans ajout de sulfites ni filtration, ce vin n'est pas vieilli en fûts de bois pour conserver sa fraîcheur caractéristique, offrant un Clarete doux et facile à boire. Les notes de dégustation révèlent un vin sur le fruit, avec des arômes floraux et minéraux. En bouche, il se distingue par sa superbe fraîcheur, une acidité équilibrée et une belle intensité. À servir bien frais, ce vin unique est idéal pour être savouré au bord de la piscine par une journée ensoleillée! Il s'accorde parfaitement avec une salade de roquette, de la betterave, avec des poissons ainsi qu'avec des fruits de mer et une paella. Une superbe découverte au prix doux!!",
      "price": "20,05 $",
      "image_url": null,
      "link": "https://bambaraselection.us1.list-manage.com/track/click?u=d2f1e39952eafd8949f464f3f&id=6c7d679ff0&e=a09c2580fc",
      "producer": "Paso a Paso",
      "region": "Argentine",
      "vintage": "2024",
      "grape_varieties": [
        "Criolla rouge",
        "Criolla blanc"
      ],
      "alcohol_content": "Nature",
      "volume": null,
      "disponibilite": "SAQ",
      "all_occurrences_raw_data": [
        {
          "name": "Paso a Paso, Criollas Clarete 2024",
          "description": "Un vin unique à découvrir, en exclusivité SAQ.com dès maintenant!! Découvrez le Clarete de Paso a Paso, une nouvelle expression du Clarete, ce vin argentin entre un rosé et un rouge léger, typique et rafraîchissant, élaboré à partir de cépages autochtones Criollas! Ce vin est l'incarnation parfaite du style authentique et traditionnel apprécié par plusieurs générations d'Argentins dans leur vie quotidienne. Ce Clarete, majoritairement composé de Criolla rouge avec une touche de Criolla blanc, est issu de vieilles vignes de 80 ans cultivées sans pesticides dans un sol argileux profond. Le pressurage doux préserve l'intégrité des baies, suivi d'une fermentation spontanée en cuves inox avec des levures indigènes. Une petite partie subit une fermentation malolactique. Sans ajout de sulfites ni filtration, ce vin n'est pas vieilli en fûts de bois pour conserver sa fraîcheur caractéristique, offrant un Clarete doux et facile à boire. Les notes de dégustation révèlent un vin sur le fruit, avec des arômes floraux et minéraux. En bouche, il se distingue par sa superbe fraîcheur, une acidité équilibrée et une belle intensité. À servir bien frais, ce vin unique est idéal pour être savouré au bord de la piscine par une journée ensoleillée! Il s'accorde parfaitement avec une salade de roquette, de la betterave, avec des poissons ainsi qu'avec des fruits de mer et une paella. Une superbe découverte au prix doux!!",
          "price": "20,05 $",
          "image_url": null,
          "link": "https://bambaraselection.us1.list-manage.com/track/click?u=d2f1e39952eafd8949f464f3f&id=6c7d679ff0&e=a09c2580fc",
          "producer": "Paso a Paso",
          "region": "Argentine",
          "vintage": "2024",
          "grape_varieties": [
            "Criolla rouge",
            "Criolla blanc"
          ],
          "alcohol_content": "Nature",
          "volume": null,
          "disponibilite": "SAQ"
        }
      ],
      "agence_was_defaulted": false
    },
    "summary": "Le Clarete de Paso a Paso, un vin argentin entre rosé et rouge léger, séduit par sa fraîcheur et ses arômes floraux, parfait pour des moments ensoleillés au bord de la piscine."
  },
  {
    "id": "file-2025-08-28-bambara-selection-0.html-xavier-gerard-saint-joseph-le-blanchard-2023",
    "blockId": "file-2025-08-28-bambara-selection-0.html",
    "createdAt": "2025-08-28T00:00:00.000Z",
    "name": "Xavier Gérard, Saint-Joseph Le Blanchard 2023",
    "description": "Enfin de retour, sur un très grand millésime!! Un patrimoine précieux et l’excellence du Rhône! Vigneron emblématique du Rhône Nord, Xavier Gérard a hérité de son père un domaine exceptionnel, s'étendant de la Côte Rôtie au Condrieu, jusqu'au Saint-Joseph. Dans ces vignobles où les pentes raides imposent un travail manuel, Xavier cultive la vigne avec un souci du détail hors pair, dans le respect des traditions et de l'environnement. Le Saint-Joseph Rouge Le Blanchard provient d'un tout petit vignoble unique au terroir exceptionnel à Chavanay, au sud de Condrieu. La fermentation spontanée et l'élevage en vieux fûts demi-muids sont au cœur de la méthode de Xavier Gérard. Cette approche permet aux vins de développer une profondeur et une complexité qui reflètent fidèlement la qualité de leur terroir. Ce Saint-Joseph dévoile une robe rouge profonde, où des notes de fruits noirs se mêlent à des notes épicées et florales, soutenues par une structure délicate et une acidité bien équilibrée. Le Blanchard se distingue par son style unique, alliant fraicheur, une belle minéralité et des arômes floraux et de baies, dans une expression plus raffinée que le Saint-Joseph typique. Sa finale est à la fois élégante et persistante. Ce vin se marie parfaitement avec une variété de plats, des viandes rouges aux gibiers, et les fromages affinés. Il peut également accompagner des mets épicés ou des options végétariennes élaborées. Ce vin est une véritable célébration du Rhône Nord, un reflet du savoir-faire et de la passion de Xavier Gérard, marquant l'union entre tradition et modernité! Une grande cuvée disponible en quantités très limitées!",
    "price": "63,00 $",
    "image_url": null,
    "link": "https://bambaraselection.us1.list-manage.com/track/click?u=d2f1e39952eafd8949f464f3f&id=b7336dab38&e=a09c2580fc",
    "agence": "Bambara Selection",
    "disponibilite": null,
    "raw_data": {
      "name": "Xavier Gérard, Saint-Joseph Le Blanchard 2023",
      "description": "Enfin de retour, sur un très grand millésime!! Un patrimoine précieux et l’excellence du Rhône! Vigneron emblématique du Rhône Nord, Xavier Gérard a hérité de son père un domaine exceptionnel, s'étendant de la Côte Rôtie au Condrieu, jusqu'au Saint-Joseph. Dans ces vignobles où les pentes raides imposent un travail manuel, Xavier cultive la vigne avec un souci du détail hors pair, dans le respect des traditions et de l'environnement. Le Saint-Joseph Rouge Le Blanchard provient d'un tout petit vignoble unique au terroir exceptionnel à Chavanay, au sud de Condrieu. La fermentation spontanée et l'élevage en vieux fûts demi-muids sont au cœur de la méthode de Xavier Gérard. Cette approche permet aux vins de développer une profondeur et une complexité qui reflètent fidèlement la qualité de leur terroir. Ce Saint-Joseph dévoile une robe rouge profonde, où des notes de fruits noirs se mêlent à des notes épicées et florales, soutenues par une structure délicate et une acidité bien équilibrée. Le Blanchard se distingue par son style unique, alliant fraicheur, une belle minéralité et des arômes floraux et de baies, dans une expression plus raffinée que le Saint-Joseph typique. Sa finale est à la fois élégante et persistante. Ce vin se marie parfaitement avec une variété de plats, des viandes rouges aux gibiers, et les fromages affinés. Il peut également accompagner des mets épicés ou des options végétariennes élaborées. Ce vin est une véritable célébration du Rhône Nord, un reflet du savoir-faire et de la passion de Xavier Gérard, marquant l'union entre tradition et modernité! Une grande cuvée disponible en quantités très limitées!",
      "price": "63,00 $",
      "image_url": null,
      "link": "https://bambaraselection.us1.list-manage.com/track/click?u=d2f1e39952eafd8949f464f3f&id=b7336dab38&e=a09c2580fc",
      "producer": "Xavier Gérard",
      "region": "Rhône",
      "vintage": "2023",
      "grape_varieties": null,
      "alcohol_content": "Biologique",
      "volume": null,
      "disponibilite": null,
      "all_occurrences_raw_data": [
        {
          "name": "Xavier Gérard, Saint-Joseph Le Blanchard 2023",
          "description": "Enfin de retour, sur un très grand millésime!! Un patrimoine précieux et l’excellence du Rhône! Vigneron emblématique du Rhône Nord, Xavier Gérard a hérité de son père un domaine exceptionnel, s'étendant de la Côte Rôtie au Condrieu, jusqu'au Saint-Joseph. Dans ces vignobles où les pentes raides imposent un travail manuel, Xavier cultive la vigne avec un souci du détail hors pair, dans le respect des traditions et de l'environnement. Le Saint-Joseph Rouge Le Blanchard provient d'un tout petit vignoble unique au terroir exceptionnel à Chavanay, au sud de Condrieu. La fermentation spontanée et l'élevage en vieux fûts demi-muids sont au cœur de la méthode de Xavier Gérard. Cette approche permet aux vins de développer une profondeur et une complexité qui reflètent fidèlement la qualité de leur terroir. Ce Saint-Joseph dévoile une robe rouge profonde, où des notes de fruits noirs se mêlent à des notes épicées et florales, soutenues par une structure délicate et une acidité bien équilibrée. Le Blanchard se distingue par son style unique, alliant fraicheur, une belle minéralité et des arômes floraux et de baies, dans une expression plus raffinée que le Saint-Joseph typique. Sa finale est à la fois élégante et persistante. Ce vin se marie parfaitement avec une variété de plats, des viandes rouges aux gibiers, et les fromages affinés. Il peut également accompagner des mets épicés ou des options végétariennes élaborées. Ce vin est une véritable célébration du Rhône Nord, un reflet du savoir-faire et de la passion de Xavier Gérard, marquant l'union entre tradition et modernité! Une grande cuvée disponible en quantités très limitées!",
          "price": "63,00 $",
          "image_url": null,
          "link": "https://bambaraselection.us1.list-manage.com/track/click?u=d2f1e39952eafd8949f464f3f&id=b7336dab38&e=a09c2580fc",
          "producer": "Xavier Gérard",
          "region": "Rhône",
          "vintage": "2023",
          "grape_varieties": null,
          "alcohol_content": "Biologique",
          "volume": null,
          "disponibilite": null
        }
      ],
      "agence_was_defaulted": false
    },
    "summary": "Le Saint-Joseph Rouge Le Blanchard de Xavier Gérard, issu d'un vignoble d'exception, révèle une profondeur et une complexité uniques, alliant fraîcheur et élégance dans une finale persistante."
  },
  {
    "id": "file-2025-08-28-info-symbiose-0.html-zarate",
    "blockId": "file-2025-08-28-info-symbiose-0.html",
    "createdAt": "2025-08-28T00:00:00.000Z",
    "name": "Zarate",
    "description": "Albarino\nL'Espagne Verte — Espagne",
    "price": "27,75 $",
    "image_url": "https://www.saq.com/media/catalog/product/1/3/13529202-1_1578537016.png",
    "link": "https://lnk_a1000004144.centrixmail.com/fr/redir.awp?idccp=1190290&idl=1525&db=GqyTLqpzI2IxBzbw4LxH23c4VfDnfXZ9GOk&ck=6wOZAbKLmJhEAArVOtbSxx2YXi5Lx1oEi1O71URzQlQ",
    "agence": "Info Symbiose",
    "disponibilite": "SAQ",
    "raw_data": {
      "name": "Zarate",
      "description": "Albarino\nL'Espagne Verte — Espagne",
      "price": "27,75 $",
      "image_url": "https://www.saq.com/media/catalog/product/1/3/13529202-1_1578537016.png",
      "link": "https://lnk_a1000004144.centrixmail.com/fr/redir.awp?idccp=1190290&idl=1525&db=GqyTLqpzI2IxBzbw4LxH23c4VfDnfXZ9GOk&ck=6wOZAbKLmJhEAArVOtbSxx2YXi5Lx1oEi1O71URzQlQ",
      "producer": "Eulogio Pomare",
      "region": "L'Espagne Verte — Espagne",
      "vintage": "2024",
      "grape_varieties": [
        "Albarino"
      ],
      "alcohol_content": null,
      "volume": null,
      "disponibilite": "SAQ",
      "all_occurrences_raw_data": [
        {
          "name": "Zarate",
          "description": "Albarino\nL'Espagne Verte — Espagne",
          "price": "27,75 $",
          "image_url": "https://www.saq.com/media/catalog/product/1/3/13529202-1_1578537016.png",
          "link": "https://lnk_a1000004144.centrixmail.com/fr/redir.awp?idccp=1190290&idl=1525&db=GqyTLqpzI2IxBzbw4LxH23c4VfDnfXZ9GOk&ck=6wOZAbKLmJhEAArVOtbSxx2YXi5Lx1oEi1O71URzQlQ",
          "producer": "Eulogio Pomare",
          "region": "L'Espagne Verte — Espagne",
          "vintage": "2024",
          "grape_varieties": [
            "Albarino"
          ],
          "alcohol_content": null,
          "volume": null,
          "disponibilite": "SAQ"
        }
      ],
      "agence_was_defaulted": false
    }
  },
  {
    "id": "file-2025-08-28-info-symbiose-0.html-arbois-terre-de-marne",
    "blockId": "file-2025-08-28-info-symbiose-0.html",
    "createdAt": "2025-08-28T00:00:00.000Z",
    "name": "Arbois Terre de Marne",
    "description": "Chardonnay\nJura — France",
    "price": "29,05 $",
    "image_url": "https://www.saq.com/media/catalog/product/1/4/14024644-1_1578549322.png",
    "link": "https://lnk_a1000004144.centrixmail.com/fr/redir.awp?idccp=1190290&idl=1775&db=GqyTLqpzI2IxBzbw4LxH23c4VfDnfXZ9GOk&ck=Z4bdbqbYRRhkGpsXWLoH80odw8wuZuG7UZ0jvEL5Bfo",
    "agence": "Info Symbiose",
    "disponibilite": "SAQ",
    "raw_data": {
      "name": "Arbois Terre de Marne",
      "description": "Chardonnay\nJura — France",
      "price": "29,05 $",
      "image_url": "https://www.saq.com/media/catalog/product/1/4/14024644-1_1578549322.png",
      "link": "https://lnk_a1000004144.centrixmail.com/fr/redir.awp?idccp=1190290&idl=1775&db=GqyTLqpzI2IxBzbw4LxH23c4VfDnfXZ9GOk&ck=Z4bdbqbYRRhkGpsXWLoH80odw8wuZuG7UZ0jvEL5Bfo",
      "producer": "Domaine Daniel Dugois",
      "region": "Jura — France",
      "vintage": "2023",
      "grape_varieties": [
        "Chardonnay"
      ],
      "alcohol_content": null,
      "volume": null,
      "disponibilite": "SAQ",
      "all_occurrences_raw_data": [
        {
          "name": "Arbois Terre de Marne",
          "description": "Chardonnay\nJura — France",
          "price": "29,05 $",
          "image_url": "https://www.saq.com/media/catalog/product/1/4/14024644-1_1578549322.png",
          "link": "https://lnk_a1000004144.centrixmail.com/fr/redir.awp?idccp=1190290&idl=1775&db=GqyTLqpzI2IxBzbw4LxH23c4VfDnfXZ9GOk&ck=Z4bdbqbYRRhkGpsXWLoH80odw8wuZuG7UZ0jvEL5Bfo",
          "producer": "Domaine Daniel Dugois",
          "region": "Jura — France",
          "vintage": "2023",
          "grape_varieties": [
            "Chardonnay"
          ],
          "alcohol_content": null,
          "volume": null,
          "disponibilite": "SAQ"
        }
      ],
      "agence_was_defaulted": false
    }
  },
  {
    "id": "file-2025-08-28-le-vin-dans-les-voiles-0.html-chateau-de-lavernette",
    "blockId": "file-2025-08-28-le-vin-dans-les-voiles-0.html",
    "createdAt": "2025-08-28T00:00:00.000Z",
    "name": "Château de Lavernette",
    "description": "Au sud de la Bourgogne, à la frontière du Mâconnais et du Beaujolais, le Château de Lavernette cultive la vigne depuis treize générations. Propriété familiale depuis 1596, le domaine compte 13 hectares menés en agriculture biologique et biodynamique (certifications AB et Demeter). Depuis 2007, Xavier de Boissieu et son épouse Kerrie perpétuent la tradition avec un style droit, précis et élégant. Leurs vins – gamay et chardonnay sur sols granitiques et calcaires – expriment avec justesse le terroir, offrant profondeur et belle capacité de garde. Cuvées nettes, tendues et vibrantes : parfaites pour les grandes tables et les amateurs en quête de vins authentiques et d’appellations de caractère. Une adresse discrète mais incontournable pour les connaisseurs.",
    "price": null,
    "image_url": "https://d3k81ch9hvuctc.cloudfront.net/company/VbA62P/images/8ae2f6fb-89d9-40b3-97df-1ecfd670cefa.png",
    "link": "https://ctrk.klclick.com/l/01K3R9MXTA87J45RTRTBQJCKEV_18",
    "agence": "Le vin dans les voiles",
    "disponibilite": null,
    "raw_data": {
      "name": "Château de Lavernette",
      "description": "Au sud de la Bourgogne, à la frontière du Mâconnais et du Beaujolais, le Château de Lavernette cultive la vigne depuis treize générations. Propriété familiale depuis 1596, le domaine compte 13 hectares menés en agriculture biologique et biodynamique (certifications AB et Demeter). Depuis 2007, Xavier de Boissieu et son épouse Kerrie perpétuent la tradition avec un style droit, précis et élégant. Leurs vins – gamay et chardonnay sur sols granitiques et calcaires – expriment avec justesse le terroir, offrant profondeur et belle capacité de garde. Cuvées nettes, tendues et vibrantes : parfaites pour les grandes tables et les amateurs en quête de vins authentiques et d’appellations de caractère. Une adresse discrète mais incontournable pour les connaisseurs.",
      "price": null,
      "image_url": "https://d3k81ch9hvuctc.cloudfront.net/company/VbA62P/images/8ae2f6fb-89d9-40b3-97df-1ecfd670cefa.png",
      "link": "https://ctrk.klclick.com/l/01K3R9MXTA87J45RTRTBQJCKEV_18",
      "producer": "Château de Lavernette",
      "region": "Bourgogne",
      "vintage": null,
      "grape_varieties": [
        "gamay",
        "chardonnay"
      ],
      "alcohol_content": null,
      "volume": null,
      "disponibilite": null,
      "all_occurrences_raw_data": [
        {
          "name": "Château de Lavernette",
          "description": "Au sud de la Bourgogne, à la frontière du Mâconnais et du Beaujolais, le Château de Lavernette cultive la vigne depuis treize générations. Propriété familiale depuis 1596, le domaine compte 13 hectares menés en agriculture biologique et biodynamique (certifications AB et Demeter). Depuis 2007, Xavier de Boissieu et son épouse Kerrie perpétuent la tradition avec un style droit, précis et élégant. Leurs vins – gamay et chardonnay sur sols granitiques et calcaires – expriment avec justesse le terroir, offrant profondeur et belle capacité de garde. Cuvées nettes, tendues et vibrantes : parfaites pour les grandes tables et les amateurs en quête de vins authentiques et d’appellations de caractère. Une adresse discrète mais incontournable pour les connaisseurs.",
          "price": null,
          "image_url": "https://d3k81ch9hvuctc.cloudfront.net/company/VbA62P/images/8ae2f6fb-89d9-40b3-97df-1ecfd670cefa.png",
          "link": "https://ctrk.klclick.com/l/01K3R9MXTA87J45RTRTBQJCKEV_18",
          "producer": "Château de Lavernette",
          "region": "Bourgogne",
          "vintage": null,
          "grape_varieties": [
            "gamay",
            "chardonnay"
          ],
          "alcohol_content": null,
          "volume": null,
          "disponibilite": null
        }
      ],
      "agence_was_defaulted": false
    },
    "summary": "Le Château de Lavernette, domaine familial en biodynamie, propose des vins de Gamay et Chardonnay qui expriment la profondeur et l'authenticité de leur terroir bourguignon, parfaits pour les grandes tables."
  },
  {
    "id": "file-2025-08-28-rezin-0.html-chorey",
    "blockId": "file-2025-08-28-rezin-0.html",
    "createdAt": "2025-08-28T00:00:00.000Z",
    "name": "Chorey",
    "description": "« Ce beau pinot de Bourgogne s’avère frais, fruité et très élégant. Élaboré dans un style classique, cet excellent Chorey plaira aux amateurs de Bourgogne aux allures davantage traditionnelles. Son nez dégage des arômes de fruits rouges, rehaussés de notes légèrement florales. Plus frais que mûr, ce très beau pinot se veut charmeur et particulièrement facile à boire. Servez ce Bourgogne moyennement corsé et équilibré, avec des grillades de volaille. Un peu cher vous direz, mais que voulez-vous, c’est la Bourgogne ! »",
    "price": null,
    "image_url": null,
    "link": null,
    "agence": "réZin",
    "disponibilite": null,
    "raw_data": {
      "name": "Chorey",
      "description": "« Ce beau pinot de Bourgogne s’avère frais, fruité et très élégant. Élaboré dans un style classique, cet excellent Chorey plaira aux amateurs de Bourgogne aux allures davantage traditionnelles. Son nez dégage des arômes de fruits rouges, rehaussés de notes légèrement florales. Plus frais que mûr, ce très beau pinot se veut charmeur et particulièrement facile à boire. Servez ce Bourgogne moyennement corsé et équilibré, avec des grillades de volaille. Un peu cher vous direz, mais que voulez-vous, c’est la Bourgogne ! »",
      "price": null,
      "image_url": null,
      "link": null,
      "producer": null,
      "region": null,
      "vintage": null,
      "grape_varieties": null,
      "alcohol_content": null,
      "volume": null,
      "disponibilite": null,
      "all_occurrences_raw_data": [
        {
          "name": "Chorey",
          "description": "« Ce beau pinot de Bourgogne s’avère frais, fruité et très élégant. Élaboré dans un style classique, cet excellent Chorey plaira aux amateurs de Bourgogne aux allures davantage traditionnelles. Son nez dégage des arômes de fruits rouges, rehaussés de notes légèrement florales. Plus frais que mûr, ce très beau pinot se veut charmeur et particulièrement facile à boire. Servez ce Bourgogne moyennement corsé et équilibré, avec des grillades de volaille. Un peu cher vous direz, mais que voulez-vous, c’est la Bourgogne ! »",
          "price": null,
          "image_url": null,
          "link": null,
          "producer": null,
          "region": null,
          "vintage": null,
          "grape_varieties": null,
          "alcohol_content": null,
          "volume": null,
          "disponibilite": null
        }
      ],
      "agence_was_defaulted": false
    },
    "summary": "Ce Chorey, un Pinot Noir classique de Bourgogne, séduit par sa fraîcheur et ses arômes de fruits rouges, offrant une élégance charmeuse et une buvabilité exceptionnelle."
  },
  {
    "id": "file-2025-08-28-rezin-0.html-morgon",
    "blockId": "file-2025-08-28-rezin-0.html",
    "createdAt": "2025-08-28T00:00:00.000Z",
    "name": "Morgon",
    "description": "« La famille Foillard fait partie de l’élite du Beaujolais. Du vin générique aux grandes cuvées parcellaires, tout est simplement excellent. Après un millésime 2021 plus difficile (mais avec des vins d’une impressionnante qualité), nous sommes de retour sur des bases plus classiques. Un profil naturel parfaitement maîtrisé qui «morgonne» à fond avec des parfums affriolants de cerises, d’eucalyptus, de réglisse et de pierre mouillée. En bouche, on devine un fruité dodu, une acidité énergique, des tanins coulants et une longueur aromatique du plus bel effet. Indice de picolabilité élevé. Servir assez frais à l’apéro, seul ou avec une planche de charcuteries. Bonheur assuré..»",
    "price": "38,25 $",
    "image_url": "https://mcusercontent.com/f9dbc793775ee9e91677594b0/images/8fe1ee76-6a7e-996f-d568-413fa2e85781.png",
    "link": "https://rezin.us8.list-manage.com/track/click?u=f9dbc793775ee9e91677594b0&id=93b5c021ac&e=c11422f941",
    "agence": "réZin",
    "disponibilite": "SAQ",
    "raw_data": {
      "name": "Morgon",
      "description": "« La famille Foillard fait partie de l’élite du Beaujolais. Du vin générique aux grandes cuvées parcellaires, tout est simplement excellent. Après un millésime 2021 plus difficile (mais avec des vins d’une impressionnante qualité), nous sommes de retour sur des bases plus classiques. Un profil naturel parfaitement maîtrisé qui «morgonne» à fond avec des parfums affriolants de cerises, d’eucalyptus, de réglisse et de pierre mouillée. En bouche, on devine un fruité dodu, une acidité énergique, des tanins coulants et une longueur aromatique du plus bel effet. Indice de picolabilité élevé. Servir assez frais à l’apéro, seul ou avec une planche de charcuteries. Bonheur assuré..»",
      "price": "38,25 $",
      "image_url": "https://mcusercontent.com/f9dbc793775ee9e91677594b0/images/8fe1ee76-6a7e-996f-d568-413fa2e85781.png",
      "link": "https://rezin.us8.list-manage.com/track/click?u=f9dbc793775ee9e91677594b0&id=93b5c021ac&e=c11422f941",
      "producer": "JEAN FOILLARD",
      "region": "Beaujolais",
      "vintage": "2023",
      "grape_varieties": null,
      "alcohol_content": null,
      "volume": null,
      "disponibilite": "SAQ",
      "all_occurrences_raw_data": [
        {
          "name": "Morgon",
          "description": "« La famille Foillard fait partie de l’élite du Beaujolais. Du vin générique aux grandes cuvées parcellaires, tout est simplement excellent. Après un millésime 2021 plus difficile (mais avec des vins d’une impressionnante qualité), nous sommes de retour sur des bases plus classiques. Un profil naturel parfaitement maîtrisé qui «morgonne» à fond avec des parfums affriolants de cerises, d’eucalyptus, de réglisse et de pierre mouillée. En bouche, on devine un fruité dodu, une acidité énergique, des tanins coulants et une longueur aromatique du plus bel effet. Indice de picolabilité élevé. Servir assez frais à l’apéro, seul ou avec une planche de charcuteries. Bonheur assuré..»",
          "price": "38,25 $",
          "image_url": "https://mcusercontent.com/f9dbc793775ee9e91677594b0/images/8fe1ee76-6a7e-996f-d568-413fa2e85781.png",
          "link": "https://rezin.us8.list-manage.com/track/click?u=f9dbc793775ee9e91677594b0&id=93b5c021ac&e=c11422f941",
          "producer": "JEAN FOILLARD",
          "region": "Beaujolais",
          "vintage": "2023",
          "grape_varieties": null,
          "alcohol_content": null,
          "volume": null,
          "disponibilite": "SAQ"
        }
      ],
      "agence_was_defaulted": false
    },
    "summary": "Le Morgon de la famille Foillard, emblématique du Beaujolais, offre un profil naturel avec des arômes de cerises et d'eucalyptus, une acidité énergique et une longueur aromatique séduisante."
  },
  {
    "id": "file-2025-08-28-rezin-0.html-manzanilla-sanlucar-de-barrameda-en-rama",
    "blockId": "file-2025-08-28-rezin-0.html",
    "createdAt": "2025-08-28T00:00:00.000Z",
    "name": "Manzanilla Sanlucar de Barrameda en Rama",
    "description": "Si Emilio Lustau est l'une des maisons de Jerez les plus appréciées, c'est sans aucun doute grâce à la qualité des sources d'approvisionnement en vendanges, moûts et vins. Cette très vieille entreprise a en effet débuté son opération en tant qu'Almacenista, c'est-à-dire en tant que petit éleveur de vin, ce qui lui permet aujourd'hui d'être en relation étroite avec les autres Almacenistas de la région. On trouve donc chez Lustau des vins issus d'assemblages de très vieux xérès provenant de différents Almacenistas. Cette proportion de vieux xérès permet d'obtenir complexité, race et finesse. À Sanlúcar, les conditions climatiques durant l’hiver ont été moins rigoureuses, avec un taux d’humidité élevé et une forte présence du vent de Poniente, ce qui a favorisé un voile de flor plus constant. Cela se reflète dans la fraîcheur unique et la texture en bouche de cette manzanilla.",
    "price": "34,00 $",
    "image_url": "https://mcusercontent.com/f9dbc793775ee9e91677594b0/images/8dbec78e-c824-5436-2f26-8d9e3de16a06.png",
    "link": "https://rezin.us8.list-manage.com/track/click?u=f9dbc793775ee9e91677594b0&id=890e7e4ac0&e=c11422f941",
    "agence": "réZin",
    "disponibilite": "SAQ",
    "raw_data": {
      "name": "Manzanilla Sanlucar de Barrameda en Rama",
      "description": "Si Emilio Lustau est l'une des maisons de Jerez les plus appréciées, c'est sans aucun doute grâce à la qualité des sources d'approvisionnement en vendanges, moûts et vins. Cette très vieille entreprise a en effet débuté son opération en tant qu'Almacenista, c'est-à-dire en tant que petit éleveur de vin, ce qui lui permet aujourd'hui d'être en relation étroite avec les autres Almacenistas de la région. On trouve donc chez Lustau des vins issus d'assemblages de très vieux xérès provenant de différents Almacenistas. Cette proportion de vieux xérès permet d'obtenir complexité, race et finesse. À Sanlúcar, les conditions climatiques durant l’hiver ont été moins rigoureuses, avec un taux d’humidité élevé et une forte présence du vent de Poniente, ce qui a favorisé un voile de flor plus constant. Cela se reflète dans la fraîcheur unique et la texture en bouche de cette manzanilla.",
      "price": "34,00 $",
      "image_url": "https://mcusercontent.com/f9dbc793775ee9e91677594b0/images/8dbec78e-c824-5436-2f26-8d9e3de16a06.png",
      "link": "https://rezin.us8.list-manage.com/track/click?u=f9dbc793775ee9e91677594b0&id=890e7e4ac0&e=c11422f941",
      "producer": "EMILIO LUSTAU",
      "region": "Jerez",
      "vintage": null,
      "grape_varieties": null,
      "alcohol_content": null,
      "volume": null,
      "disponibilite": "SAQ",
      "all_occurrences_raw_data": [
        {
          "name": "Manzanilla Sanlucar de Barrameda en Rama",
          "description": "Si Emilio Lustau est l'une des maisons de Jerez les plus appréciées, c'est sans aucun doute grâce à la qualité des sources d'approvisionnement en vendanges, moûts et vins. Cette très vieille entreprise a en effet débuté son opération en tant qu'Almacenista, c'est-à-dire en tant que petit éleveur de vin, ce qui lui permet aujourd'hui d'être en relation étroite avec les autres Almacenistas de la région. On trouve donc chez Lustau des vins issus d'assemblages de très vieux xérès provenant de différents Almacenistas. Cette proportion de vieux xérès permet d'obtenir complexité, race et finesse. À Sanlúcar, les conditions climatiques durant l’hiver ont été moins rigoureuses, avec un taux d’humidité élevé et une forte présence du vent de Poniente, ce qui a favorisé un voile de flor plus constant. Cela se reflète dans la fraîcheur unique et la texture en bouche de cette manzanilla.",
          "price": "34,00 $",
          "image_url": "https://mcusercontent.com/f9dbc793775ee9e91677594b0/images/8dbec78e-c824-5436-2f26-8d9e3de16a06.png",
          "link": "https://rezin.us8.list-manage.com/track/click?u=f9dbc793775ee9e91677594b0&id=890e7e4ac0&e=c11422f941",
          "producer": "EMILIO LUSTAU",
          "region": "Jerez",
          "vintage": null,
          "grape_varieties": null,
          "alcohol_content": null,
          "volume": null,
          "disponibilite": "SAQ"
        }
      ],
      "agence_was_defaulted": false
    },
    "summary": "La Manzanilla Sanlucar de Barrameda en Rama de Lustau, issue de vieux xérès, offre une complexité et une finesse exceptionnelles, avec une fraîcheur unique grâce à son voile de flor."
  },
  {
    "id": "file-2025-08-27-vin-dame-jeanne-0.html-champagne-ludes-1er-cru-reflet-dantan-brut",
    "blockId": "file-2025-08-27-vin-dame-jeanne-0.html",
    "createdAt": "2025-08-27T00:00:00.000Z",
    "name": "Champagne, Ludes 1er cru 'Reflet d'Antan', Brut",
    "description": "Réserve perpétuelle issue de Pierre Bérêche, transmise et mis en bouteille par Jean-Pierre Bérêche depuis 1990. Cette cuvée est le reflet du Champagne d’Antan. La famille Bérêche a souhaité protéger cette cuvée avec un format magnum, le contenant idéal et sans concession. 36 mois sur lattes. De cette cuvée se dégage des arômes mâtures et complexes de fruits confits, nougat, génoise. Nous sommes également sur des arômes tertiaires avec des notes de sous-bois et des épices. La bouche est équilibrée et assise, consistance de velours, presque chaude. Finale très longue, délicatement crayeuse et saline. L'effet magnum tiré liège boucle la boucle sur cette cuvée hautement gastronomique, poussant l'effet umami encore plus loin, et ouvrant des clés aromatiques complexes et étagées. Du grand, grand art !!",
    "price": "1,255.50$",
    "image_url": "https://gallery.mailchimp.com/0711127c320d32e15ce6dc05f/images/adf2b9d7-739a-4c47-bfb0-d1c357915531.jpg",
    "link": "https://vindamejeanne.us10.list-manage.com/track/click?u=0711127c320d32e15ce6dc05f&id=60ffac18ce&e=345e10d07b",
    "agence": "Vin Dame-Jeanne",
    "disponibilite": "SAQ",
    "raw_data": {
      "name": "Champagne, Ludes 1er cru 'Reflet d'Antan', Brut",
      "description": "Réserve perpétuelle issue de Pierre Bérêche, transmise et mis en bouteille par Jean-Pierre Bérêche depuis 1990. Cette cuvée est le reflet du Champagne d’Antan. La famille Bérêche a souhaité protéger cette cuvée avec un format magnum, le contenant idéal et sans concession. 36 mois sur lattes. De cette cuvée se dégage des arômes mâtures et complexes de fruits confits, nougat, génoise. Nous sommes également sur des arômes tertiaires avec des notes de sous-bois et des épices. La bouche est équilibrée et assise, consistance de velours, presque chaude. Finale très longue, délicatement crayeuse et saline. L'effet magnum tiré liège boucle la boucle sur cette cuvée hautement gastronomique, poussant l'effet umami encore plus loin, et ouvrant des clés aromatiques complexes et étagées. Du grand, grand art !!",
      "price": "1,255.50$",
      "image_url": "https://gallery.mailchimp.com/0711127c320d32e15ce6dc05f/images/adf2b9d7-739a-4c47-bfb0-d1c357915531.jpg",
      "link": "https://vindamejeanne.us10.list-manage.com/track/click?u=0711127c320d32e15ce6dc05f&id=60ffac18ce&e=345e10d07b",
      "producer": "Bérêche",
      "region": "Ludes 1er cru",
      "vintage": null,
      "grape_varieties": null,
      "alcohol_content": null,
      "volume": "1500ml",
      "disponibilite": "SAQ",
      "all_occurrences_raw_data": [
        {
          "name": "Champagne, Ludes 1er cru 'Reflet d'Antan', Brut",
          "description": "Réserve perpétuelle issue de Pierre Bérêche, transmise et mis en bouteille par Jean-Pierre Bérêche depuis 1990. Cette cuvée est le reflet du Champagne d’Antan. La famille Bérêche a souhaité protéger cette cuvée avec un format magnum, le contenant idéal et sans concession. 36 mois sur lattes. De cette cuvée se dégage des arômes mâtures et complexes de fruits confits, nougat, génoise. Nous sommes également sur des arômes tertiaires avec des notes de sous-bois et des épices. La bouche est équilibrée et assise, consistance de velours, presque chaude. Finale très longue, délicatement crayeuse et saline. L'effet magnum tiré liège boucle la boucle sur cette cuvée hautement gastronomique, poussant l'effet umami encore plus loin, et ouvrant des clés aromatiques complexes et étagées. Du grand, grand art !!",
          "price": "1,255.50$",
          "image_url": "https://gallery.mailchimp.com/0711127c320d32e15ce6dc05f/images/adf2b9d7-739a-4c47-bfb0-d1c357915531.jpg",
          "link": "https://vindamejeanne.us10.list-manage.com/track/click?u=0711127c320d32e15ce6dc05f&id=60ffac18ce&e=345e10d07b",
          "producer": "Bérêche",
          "region": "Ludes 1er cru",
          "vintage": null,
          "grape_varieties": null,
          "alcohol_content": null,
          "volume": "1500ml",
          "disponibilite": "SAQ"
        }
      ],
      "agence_was_defaulted": false
    },
    "summary": "Le Champagne Ludes 1er cru 'Reflet d'Antan', en magnum, révèle des arômes complexes de fruits confits et d'épices, offrant une bouche veloutée et une finale longue et saline, une véritable œuvre d'art gastronomique."
  },
  {
    "id": "file-2025-08-26-planvin-0.html-gargante-2022",
    "blockId": "file-2025-08-26-planvin-0.html",
    "createdAt": "2025-08-26T00:00:00.000Z",
    "name": "Gargànte 2022",
    "description": "Une bulle de soif, sur lie, refermentée en bouteille. 100 % garganega, vinifiée spontanément en cuve inox. Élevage d’environ 5 mois sur lies en cuves béton. La prise de mousse se fait naturellement en bouteille, par ajout de moût de garganega passerillé. Robe jaune paille, mousse généreuse. La bouche est fraîche, ample, portée par une trame minérale et une sapidité vibrante qui appelle la prochaine gorgée. Gargànte, c’est un vin sincère, immédiat, pensé pour la buvabilité.",
    "price": "32,46 $",
    "image_url": null,
    "link": "https://planvin.us15.list-manage.com/track/click?u=bcc803c4eada215e47355c036&id=294e8c0a64&e=bc0729f8df",
    "agence": "Planvin",
    "disponibilite": "SAQ",
    "raw_data": {
      "name": "Gargànte 2022",
      "description": "Une bulle de soif, sur lie, refermentée en bouteille. 100 % garganega, vinifiée spontanément en cuve inox. Élevage d’environ 5 mois sur lies en cuves béton. La prise de mousse se fait naturellement en bouteille, par ajout de moût de garganega passerillé. Robe jaune paille, mousse généreuse. La bouche est fraîche, ample, portée par une trame minérale et une sapidité vibrante qui appelle la prochaine gorgée. Gargànte, c’est un vin sincère, immédiat, pensé pour la buvabilité.",
      "price": "32,46 $",
      "image_url": null,
      "link": "https://planvin.us15.list-manage.com/track/click?u=bcc803c4eada215e47355c036&id=294e8c0a64&e=bc0729f8df",
      "producer": "Nevio Scala",
      "region": "IGT Veneto",
      "vintage": "2022",
      "grape_varieties": [
        "garganega"
      ],
      "alcohol_content": null,
      "volume": null,
      "disponibilite": "SAQ",
      "all_occurrences_raw_data": [
        {
          "name": "Gargànte 2022",
          "description": "Une bulle de soif, sur lie, refermentée en bouteille. 100 % garganega, vinifiée spontanément en cuve inox. Élevage d’environ 5 mois sur lies en cuves béton. La prise de mousse se fait naturellement en bouteille, par ajout de moût de garganega passerillé. Robe jaune paille, mousse généreuse. La bouche est fraîche, ample, portée par une trame minérale et une sapidité vibrante qui appelle la prochaine gorgée. Gargànte, c’est un vin sincère, immédiat, pensé pour la buvabilité.",
          "price": "32,46 $",
          "image_url": null,
          "link": "https://planvin.us15.list-manage.com/track/click?u=bcc803c4eada215e47355c036&id=294e8c0a64&e=bc0729f8df",
          "producer": "Nevio Scala",
          "region": "IGT Veneto",
          "vintage": "2022",
          "grape_varieties": [
            "garganega"
          ],
          "alcohol_content": null,
          "volume": null,
          "disponibilite": "SAQ"
        }
      ],
      "agence_was_defaulted": false
    },
    "summary": "Gargànte, un vin pétillant 100% Garganega, se distingue par sa fraîcheur et sa mousse généreuse, offrant une buvabilité immédiate et une sapidité vibrante."
  },
  {
    "id": "file-2025-08-26-planvin-0.html-blanko",
    "blockId": "file-2025-08-26-planvin-0.html",
    "createdAt": "2025-08-26T00:00:00.000Z",
    "name": "Blanko",
    "description": "Assemblage de garganega, malvasia istriana et moscato bianco issus de jeunes vignes. Ce vin est vinifié avec une courte macération pelliculaire et élevé uniquement en cuve béton. Le nez révèle des notes délicates de zeste de citron et de fleurs blanches. La bouche est vive et florale, offre une texture légère et désaltérante qui glisse toute seule sans jamais tomber dans l’excès.",
    "price": "28,97 $",
    "image_url": null,
    "link": null,
    "agence": "Planvin",
    "disponibilite": null,
    "raw_data": {
      "name": "Blanko",
      "description": "Assemblage de garganega, malvasia istriana et moscato bianco issus de jeunes vignes. Ce vin est vinifié avec une courte macération pelliculaire et élevé uniquement en cuve béton. Le nez révèle des notes délicates de zeste de citron et de fleurs blanches. La bouche est vive et florale, offre une texture légère et désaltérante qui glisse toute seule sans jamais tomber dans l’excès.",
      "price": "28,97 $",
      "image_url": null,
      "link": null,
      "producer": "Nevio Scala",
      "region": "VDT",
      "vintage": null,
      "grape_varieties": [
        "garganega",
        "malvasia istriana",
        "moscato bianco"
      ],
      "alcohol_content": null,
      "volume": null,
      "disponibilite": null,
      "all_occurrences_raw_data": [
        {
          "name": "Blanko",
          "description": "Assemblage de garganega, malvasia istriana et moscato bianco issus de jeunes vignes. Ce vin est vinifié avec une courte macération pelliculaire et élevé uniquement en cuve béton. Le nez révèle des notes délicates de zeste de citron et de fleurs blanches. La bouche est vive et florale, offre une texture légère et désaltérante qui glisse toute seule sans jamais tomber dans l’excès.",
          "price": "28,97 $",
          "image_url": null,
          "link": null,
          "producer": "Nevio Scala",
          "region": "VDT",
          "vintage": null,
          "grape_varieties": [
            "garganega",
            "malvasia istriana",
            "moscato bianco"
          ],
          "alcohol_content": null,
          "volume": null,
          "disponibilite": null
        }
      ],
      "agence_was_defaulted": false
    },
    "summary": "Blanko, assemblage de Garganega, Malvasia Istriana et Moscato Bianco, offre des arômes de citron et de fleurs blanches, avec une bouche vive et désaltérante, parfaite pour toute occasion."
  },
  {
    "id": "file-2025-08-25-vin-dame-jeanne-0.html-savigny-les-beaune-1er-cru-les-lavieres-2020",
    "blockId": "file-2025-08-25-vin-dame-jeanne-0.html",
    "createdAt": "2025-08-25T00:00:00.000Z",
    "name": "Savigny-les-Beaune 1er cru ‘Les Lavières’, 2020",
    "description": "Vignes sur la commune de Savigny-Lès-Beaune, à mi-coteaux, orientation Sud-Sud-Est. Sols à dominante argilo-calcaire posés sur un sous-sol composé de lavières. Pinot Noir issu d’une sélection massale plantée en 1954. Vinification en grappes entières : encuvage en cuve bois tronconique. Vinification sur l'extraction douce, grâce à des remontages et pigeages légers. Macération totale de 2 à 3 semaines. Élevage de 18 mois en pièces bourguignonnes. Grand Pinot Noir de table, et de garde !",
    "price": "179,37$",
    "image_url": "https://gallery.mailchimp.com/0711127c320d32e15ce6dc05f/images/adf2b9d7-739a-4c47-bfb0-d1c357915531.jpg",
    "link": null,
    "agence": "Vin Dame-Jeanne",
    "disponibilite": "Importation Privée",
    "raw_data": {
      "name": "Savigny-les-Beaune 1er cru ‘Les Lavières’, 2020",
      "description": "Vignes sur la commune de Savigny-Lès-Beaune, à mi-coteaux, orientation Sud-Sud-Est. Sols à dominante argilo-calcaire posés sur un sous-sol composé de lavières. Pinot Noir issu d’une sélection massale plantée en 1954. Vinification en grappes entières : encuvage en cuve bois tronconique. Vinification sur l'extraction douce, grâce à des remontages et pigeages légers. Macération totale de 2 à 3 semaines. Élevage de 18 mois en pièces bourguignonnes. Grand Pinot Noir de table, et de garde !",
      "price": "179,37$",
      "image_url": "https://gallery.mailchimp.com/0711127c320d32e15ce6dc05f/images/adf2b9d7-739a-4c47-bfb0-d1c357915531.jpg",
      "link": null,
      "producer": "Athénais de Béru",
      "region": "Savigny-Lès-Beaune",
      "vintage": "2020",
      "grape_varieties": [
        "Pinot Noir"
      ],
      "alcohol_content": null,
      "volume": null,
      "disponibilite": "Importation Privée",
      "all_occurrences_raw_data": [
        {
          "name": "Savigny-les-Beaune 1er cru ‘Les Lavières’, 2020",
          "description": "Vignes sur la commune de Savigny-Lès-Beaune, à mi-coteaux, orientation Sud-Sud-Est. Sols à dominante argilo-calcaire posés sur un sous-sol composé de lavières. Pinot Noir issu d’une sélection massale plantée en 1954. Vinification en grappes entières : encuvage en cuve bois tronconique. Vinification sur l'extraction douce, grâce à des remontages et pigeages légers. Macération totale de 2 à 3 semaines. Élevage de 18 mois en pièces bourguignonnes. Grand Pinot Noir de table, et de garde !",
          "price": "179,37$",
          "image_url": "https://gallery.mailchimp.com/0711127c320d32e15ce6dc05f/images/adf2b9d7-739a-4c47-bfb0-d1c357915531.jpg",
          "link": null,
          "producer": "Athénais de Béru",
          "region": "Savigny-Lès-Beaune",
          "vintage": "2020",
          "grape_varieties": [
            "Pinot Noir"
          ],
          "alcohol_content": null,
          "volume": null,
          "disponibilite": "Importation Privée"
        }
      ],
      "agence_was_defaulted": false
    },
    "summary": "Le Savigny-les-Beaune 1er cru ‘Les Lavières’ 2020, issu de vignes de 1954, offre un Pinot Noir élégant, avec une extraction douce et un potentiel de garde remarquable, parfait pour les grandes occasions."
  }
]